incremental_pca_torch/__init__.py
incremental_pca_torch/incremental_pca.py
incremental_pca_torch-0.1.0.dist-info/licenses/LICENSE
incremental_pca_torch-0.1.0.dist-info/METADATA
incremental_pca_torch-0.1.0.dist-info/WHEEL
incremental_pca_torch-0.1.0.dist-info/top_level.txt
incremental_pca_torch-0.1.0.dist-info/RECORD
