Metadata-Version: 2.4
Name: incremental-pca-torch
Version: 0.1.0
Summary: GPU-accelerated Incremental PCA using PyTorch, with sklearn-compatible API
Author: RH
License: MIT
Project-URL: Homepage, https://github.com/RichieHakim/incremental_pca
Project-URL: Repository, https://github.com/RichieHakim/incremental_pca
Project-URL: Issues, https://github.com/RichieHakim/incremental_pca/issues
Keywords: pca,incremental-pca,dimensionality-reduction,pytorch,gpu,machine-learning,out-of-core
Classifier: Development Status :: 4 - Beta
Classifier: Intended Audience :: Science/Research
Classifier: Intended Audience :: Developers
Classifier: License :: OSI Approved :: MIT License
Classifier: Programming Language :: Python :: 3
Classifier: Programming Language :: Python :: 3.8
Classifier: Programming Language :: Python :: 3.9
Classifier: Programming Language :: Python :: 3.10
Classifier: Programming Language :: Python :: 3.11
Classifier: Programming Language :: Python :: 3.12
Classifier: Topic :: Scientific/Engineering
Classifier: Topic :: Scientific/Engineering :: Artificial Intelligence
Requires-Python: >=3.8
License-File: LICENSE
Requires-Dist: torch>=1.9.0
Requires-Dist: tqdm>=4.0.0
Provides-Extra: dev
Requires-Dist: pytest>=7.0.0; extra == "dev"
Requires-Dist: pytest-cov>=4.0.0; extra == "dev"
Requires-Dist: scikit-learn>=1.0.0; extra == "dev"
Requires-Dist: numpy>=1.20.0; extra == "dev"
Dynamic: license-file
